django_responsive_tables2/__init__.py
django_responsive_tables2/apps.py
django_responsive_tables2/tests.py
django_responsive_tables2/views.py
django_responsive_tables2/static/django_responsive_tables2/tables.js
django_responsive_tables2/templates/django_responsive_tables2/basic_table.html
django_responsive_tables2/templatetags/__init__.py
django_responsive_tables2/templatetags/responsive_table.py
django_responsive_tables2-0.8.1.dist-info/LICENSE
django_responsive_tables2-0.8.1.dist-info/METADATA
django_responsive_tables2-0.8.1.dist-info/WHEEL
django_responsive_tables2-0.8.1.dist-info/top_level.txt
django_responsive_tables2-0.8.1.dist-info/RECORD
