Metadata-Version: 2.1
Name: django-responsive-tables2
Version: 0.8.1
Summary: django-tables2 with AJAX searching and pagination.
Home-page: https://github.com/LegendaryFire/django-responsive-tables2
Author: Tristan Balon
Author-email: tristan.balon@outlook.com
Classifier: Programming Language :: Python :: 3
Classifier: Framework :: Django :: 5.0
Classifier: License :: OSI Approved :: MIT License
Requires-Python: >=3.8
License-File: LICENSE
Requires-Dist: django >=5.0.0
Requires-Dist: django-tables2 >=2.7.0
